ascender/__init__.py
ascender/abc/__init__.py
ascender/abc/middleware.py
ascender/clis/__init__.py
ascender/clis/builder/__init__.py
ascender/clis/builder/build_app.py
ascender/clis/builder/build_message_service.py
ascender/clis/builder/build_service.py
ascender/clis/generator/__init__.py
ascender/clis/generator/create_generator_service.py
ascender/clis/generator/edit_generator_service.py
ascender/clis/generator/generator_app.py
ascender/clis/new/__init__.py
ascender/clis/new/new_app.py
ascender/clis/new/new_service.py
ascender/clis/run/__init__.py
ascender/clis/run/run_app.py
ascender/clis/serve/__init__.py
ascender/clis/serve/serve_app.py
ascender/clis/serve/serve_service.py
ascender/clis/tests/__init__.py
ascender/clis/tests/tests_app.py
ascender/clis/tests/tests_cli_service.py
ascender/clis/version/version_app.py
ascender/common/__init__.py
ascender/common/api/__init__.py
ascender/common/api/base_http_middleware.py
ascender/common/api/cors_middleware.py
ascender/common/api/relational_middleware.py
ascender/common/api_docs.py
ascender/common/base/__init__.py
ascender/common/base/dto.py
ascender/common/base/response.py
ascender/common/http/__init__.py
ascender/common/http/_transport.py
ascender/common/http/awaitables/awaitable.py
ascender/common/http/client.py
ascender/common/http/provider.py
ascender/common/http/types/__init__.py
ascender/common/http/types/file.py
ascender/common/http/types/formdata.py
ascender/common/http/types/http_options.py
ascender/common/http/types/interceptors.py
ascender/common/injectable.py
ascender/common/microservices/__init__.py
ascender/common/microservices/abc/__init__.py
ascender/common/microservices/abc/client_proxy.py
ascender/common/microservices/abc/context.py
ascender/common/microservices/abc/event_bus.py
ascender/common/microservices/abc/event_transport.py
ascender/common/microservices/abc/rpc_transport.py
ascender/common/microservices/abc/transporter.py
ascender/common/microservices/callback_manager.py
ascender_framework-2.0.4.dist-info/LICENSE
ascender_framework-2.0.4.dist-info/METADATA
ascender_framework-2.0.4.dist-info/WHEEL
ascender_framework-2.0.4.dist-info/entry_points.txt
ascender_framework-2.0.4.dist-info/RECORD
