Metadata-Version: 2.3
Name: ascender-framework
Version: 2.0.4
Summary: The Ascender Framework is a sophisticated and structured FastAPI-based framework, inspired by the principles of NestJS. It stands out for its modular and organized architecture, offering developers a streamlined and efficient way to build web applications
Author: AscenderTeam
Requires-Python: >=3.11,<3.14
Classifier: Programming Language :: Python :: 3
Classifier: Programming Language :: Python :: 3.11
Classifier: Programming Language :: Python :: 3.12
Classifier: Programming Language :: Python :: 3.13
Requires-Dist: aerich (>=0.7.2,<0.8.0)
Requires-Dist: chardet (>=5.2.0,<6.0.0)
Requires-Dist: click (>=8.1.7,<9.0.0)
Requires-Dist: fastapi (>=0.115)
Requires-Dist: httpx (>=0.28.1,<0.29.0)
Requires-Dist: inflection (>=0.5.1,<0.6.0)
Requires-Dist: jinja2 (>=3.1.4,<4.0.0)
Requires-Dist: mkdocs-awesome-pages-plugin (>=2.10.1,<3.0.0)
Requires-Dist: pydantic[email] (>=2.7.4)
Requires-Dist: pyinstaller (>=6.11.1,<7.0.0)
Requires-Dist: pytest (>=8.4.2,<9.0.0)
Requires-Dist: python-dotenv (>=1.0.0,<2.0.0)
Requires-Dist: python-minifier (>=2.11.3,<3.0.0)
Requires-Dist: reactivex (>=4.0.4)
Requires-Dist: readchar (>=4.0.5,<5.0.0)
Requires-Dist: requests (>=2.31.0)
Requires-Dist: rich (>=13.6.0,<14.0.0)
Requires-Dist: rich-argparse (>=1.7.1,<2.0.0)
Requires-Dist: rich-click (>=1.7.2,<2.0.0)
Requires-Dist: sqlalchemy[asyncio] (>=2.0.31)
Requires-Dist: uvicorn (>=0.25)
Requires-Dist: watchfiles (>=1.0.5,<2.0.0)
Project-URL: Homepage, https://ascender-framework.com
Project-URL: Repository, https://github.com/ascenderteam/ascenderframework
